ulp/__init__.py
ulp/main.py
ulp/tui.py
ulp/urlextract.py
ulp/widgets/__init__.py
ulp/widgets/command_line.py
ulp/widgets/link.py
ulp/widgets/listbox.py
ulp/widgets/popup.py
ulp-1.3.1.data/scripts/ulp
ulp-1.3.1.dist-info/METADATA
ulp-1.3.1.dist-info/RECORD
ulp-1.3.1.dist-info/WHEEL
ulp-1.3.1.dist-info/entry_points.txt
ulp-1.3.1.dist-info/top_level.txt
