Metadata-Version: 2.1
Name: ulp
Version: 1.3.1
Summary: ULP is a Locator Picker - a PathPicker clone for URLs
Home-page: https://github.com/victal/ulp
Author: Guilherme Victal
Author-email: guilherme@victal.eti.br
License: MIT
Platform: UNKNOWN
Classifier: Development Status :: 3 - Alpha
Classifier: Intended Audience :: Developers
Classifier: Topic :: Software Development :: Build Tools
Classifier: License :: OSI Approved :: MIT License
Classifier: Programming Language :: Python :: 3
Classifier: Programming Language :: Python :: 3.5
Requires-Dist: pyperclip (>=1.6.0)
Requires-Dist: urwid
